mfml/__init__.py
mfml/core.py
my_first_ml-0.1.6.dist-info/licenses/LICENSE
my_first_ml-0.1.6.dist-info/METADATA
my_first_ml-0.1.6.dist-info/WHEEL
my_first_ml-0.1.6.dist-info/top_level.txt
my_first_ml-0.1.6.dist-info/RECORD
