Metadata-Version: 2.4
Name: my-first-ml
Version: 0.1.6
Summary: A test package for ML explanation utilities
Author-email: Cyruss Banerjee <cyruss.banerjee@proton.me>
License-Expression: MIT
Project-URL: Homepage, https://github.com/cyruss-banerjee/my-first-ml
Project-URL: Repository, https://github.com/cyruss-banerjee/my-first-ml
Keywords: machine-learning,explanation,test
Classifier: Programming Language :: Python :: 3
Classifier: Operating System :: OS Independent
Requires-Python: >=3.7
License-File: LICENSE
Dynamic: license-file
